odoo/addons/product_category_product_qty/README.rst
odoo/addons/product_category_product_qty/__init__.py
odoo/addons/product_category_product_qty/__manifest__.py
odoo/addons/product_category_product_qty/i18n/it.po
odoo/addons/product_category_product_qty/i18n/product_category_product_qty.pot
odoo/addons/product_category_product_qty/l10n/fr.po
odoo/addons/product_category_product_qty/models/__init__.py
odoo/addons/product_category_product_qty/models/product_category.py
odoo/addons/product_category_product_qty/readme/CONTRIBUTORS.rst
odoo/addons/product_category_product_qty/readme/DESCRIPTION.rst
odoo/addons/product_category_product_qty/static/description/icon.png
odoo/addons/product_category_product_qty/static/description/index.html
odoo/addons/product_category_product_qty/static/description/product_category_form.png
odoo/addons/product_category_product_qty/static/description/product_category_tree.png
odoo/addons/product_category_product_qty/tests/__init__.py
odoo/addons/product_category_product_qty/tests/test_product_category_product_qty.py
odoo/addons/product_category_product_qty/views/view_product_category.xml
odoo_addon_product_category_product_qty-16.0.1.0.0.4.dist-info/METADATA
odoo_addon_product_category_product_qty-16.0.1.0.0.4.dist-info/WHEEL
odoo_addon_product_category_product_qty-16.0.1.0.0.4.dist-info/top_level.txt
odoo_addon_product_category_product_qty-16.0.1.0.0.4.dist-info/RECORD
